setup.py
manga_parser/__init__.py
manga_parser/client.py
manga_parser/exceptions.py
manga_parser/requests.py
manga_parser/utils.py
manga_parser.egg-info/PKG-INFO
manga_parser.egg-info/SOURCES.txt
manga_parser.egg-info/dependency_links.txt
manga_parser.egg-info/requires.txt
manga_parser.egg-info/top_level.txt
manga_parser/manga/__init__.py
manga_parser/manga/readmanga.py
manga_parser/manga/remanga.py
manga_parser/parsers/__init__.py
manga_parser/parsers/readmanga.py
manga_parser/parsers/remanga.py
manga_parser/schemas/__init__.py
manga_parser/schemas/readmanga/__init__.py
manga_parser/schemas/readmanga/chapter.py
manga_parser/schemas/readmanga/manga.py
manga_parser/schemas/readmanga/manga_briefly.py
manga_parser/schemas/readmanga/page.py
manga_parser/schemas/readmanga/translator.py
manga_parser/schemas/readmanga/translator_briefly.py
manga_parser/schemas/remanga/__init__.py
manga_parser/schemas/remanga/branch.py
manga_parser/schemas/remanga/chapter.py
manga_parser/schemas/remanga/manga.py
manga_parser/schemas/remanga/manga_average.py
manga_parser/schemas/remanga/manga_briefly.py
manga_parser/schemas/remanga/page.py
manga_parser/schemas/remanga/translator.py
manga_parser/schemas/remanga/translator_briefly.py